[
    {
        "Before Tree": [
            {
                "Label": "",
                "Type": -1589682499,
                "Children": [
                    [
                        {
                            "Label": "",
                            "Type": 3127797,
                            "Children": [
                                [
                                    {
                                        "Label": "",
                                        "Type": 3045982,
                                        "Children": [
                                            [
                                                {
                                                    "Label": "",
                                                    "Type": -40060704,
                                                    "Children": [
                                                        
                                                    ]
                                                }
                                            ],
                                            [
                                                {
                                                    "Label": "",
                                                    "Type": 3373707,
                                                    "Children": [
                                                        [
                                                            {
                                                                "Label": "ToReadable",
                                                                "Type": 3373707,
                                                                "Children": [
                                                                    
                                                                ]
                                                            }
                                                        ],
                                                        [
                                                            {
                                                                "Label": ".",
                                                                "Type": -500553564,
                                                                "Children": [
                                                                    
                                                                ]
                                                            }
                                                        ],
                                                        [
                                                            {
                                                                "Label": "listOfNumbers",
                                                                "Type": 3373707,
                                                                "Children": [
                                                                    
                                                                ]
                                                            }
                                                        ]
                                                    ]
                                                }
                                            ]
                                        ]
                                    }
                                ],
                                [
                                    {
                                        "Label": "+",
                                        "Type": -500553564,
                                        "Children": [
                                            
                                        ]
                                    }
                                ],
                                [
                                    {
                                        "Label": "?",
                                        "Type": 17200,
                                        "Children": [
                                            
                                        ]
                                    }
                                ]
                            ]
                        }
                    ]
                ]
            }
        ],
        "After Tree": [
            {
                "Label": "",
                "Type": -1589682499,
                "Children": [
                    [
                        {
                            "Label": "",
                            "Type": 3127797,
                            "Children": [
                                [
                                    {
                                        "Label": "",
                                        "Type": 3045982,
                                        "Children": [
                                            [
                                                {
                                                    "Label": "",
                                                    "Type": -40060704,
                                                    "Children": [
                                                        
                                                    ]
                                                }
                                            ],
                                            [
                                                {
                                                    "Label": "",
                                                    "Type": 3373707,
                                                    "Children": [
                                                        [
                                                            {
                                                                "Label": "ToReadable",
                                                                "Type": 3373707,
                                                                "Children": [
                                                                    
                                                                ]
                                                            }
                                                        ],
                                                        [
                                                            {
                                                                "Label": ".",
                                                                "Type": -500553564,
                                                                "Children": [
                                                                    
                                                                ]
                                                            }
                                                        ],
                                                        [
                                                            {
                                                                "Label": "listOfNumbers",
                                                                "Type": 3373707,
                                                                "Children": [
                                                                    
                                                                ]
                                                            }
                                                        ]
                                                    ]
                                                }
                                            ]
                                        ]
                                    }
                                ],
                                [
                                    {
                                        "Label": "+",
                                        "Type": -500553564,
                                        "Children": [
                                            
                                        ]
                                    }
                                ],
                                [
                                    {
                                        "Label": "?",
                                        "Type": 27200,
                                        "Children": [
                                            
                                        ]
                                    }
                                ]
                            ]
                        }
                    ]
                ]
            }
        ],
        "Left": 265,
        "Right": 1201592,
        "Commit id's": [
            "f657ff559ed0950ae7b712f5d56e1224d394107e",
            "f657ff559ed0950ae7b712f5d56e1224d394107e",
            "f657ff559ed0950ae7b712f5d56e1224d394107e"
        ]
    }
]